typeFX/__init__.py
typeFX/type.py
typeFX-0.1.2.dist-info/LICENSE
typeFX-0.1.2.dist-info/METADATA
typeFX-0.1.2.dist-info/WHEEL
typeFX-0.1.2.dist-info/top_level.txt
typeFX-0.1.2.dist-info/RECORD
